sheenroo_algs/__init__.py
sheenroo_algs-1.0.dist-info/LICENSE
sheenroo_algs-1.0.dist-info/METADATA
sheenroo_algs-1.0.dist-info/WHEEL
sheenroo_algs-1.0.dist-info/top_level.txt
sheenroo_algs-1.0.dist-info/RECORD
