Metadata-Version: 2.1
Name: sheenroo-algs
Version: 1.0
Summary: Ein Python-Modul für verschiedene Algorithmen
Home-page: https://github.com/xinru1414/sheenroo_algs
Author: SheenRoo die chinesische Prinzessin
Author-email: xinru1414@gmail.com
License: MIT
Platform: UNKNOWN
